jonschema/__init__.py
jonschema-0.1.1.dist-info/LICENSE.txt
jonschema-0.1.1.dist-info/METADATA
jonschema-0.1.1.dist-info/WHEEL
jonschema-0.1.1.dist-info/top_level.txt
jonschema-0.1.1.dist-info/RECORD
