Metadata-Version: 2.1
Name: jonschema
Version: 0.1.1
Summary: jonschema is a dependency allowing you to validate multiple data types in a precise and fast way
Home-page: https://ntouba98@bitbucket.org/ntouba98/jonschema.git
Download-URL: https://pypi.org/project/jonschema/
Author: BILOG NTOUBA Célestin
Author-email: ntoubacelestin98@gmail.com
License: MIT
Keywords: schema,validator,json,hivi
Platform: UNKNOWN
License-File: LICENSE.txt
Requires-Dist: python (>2.0)
Requires-Dist: Django (>1.0)
